{
  "last_page": "/movies?page=338&page_size=30",
  "movies": [
    {
      "Year": 1894,
      "bechdelScore": 0,
      "bechdelTest": "False",
      "englishTitle": "Carmencita",
      "isAdult": 1,
      "movieId": 1,
      "movieType": "short",
      "originalTitle": "Carmencita",
      "runtimeMinutes": "1"
    },
    {
      "Year": 1892,
      "bechdelScore": 0,
      "bechdelTest": "False",
      "englishTitle": "Le clown et ses chiens",
      "isAdult": 1,
      "movieId": 2,
      "movieType": "short",
      "originalTitle": "Le clown et ses chiens",
      "runtimeMinutes": "5"
    },
    {
      "Year": 1892,
      "bechdelScore": 0,
      "bechdelTest": "False",
      "englishTitle": "Pauvre Pierrot",
      "isAdult": 1,
      "movieId": 3,
      "movieType": "short",
      "originalTitle": "Pauvre Pierrot",
      "runtimeMinutes": "4"
    },
    {
      "Year": 1892,
      "bechdelScore": 0,
      "bechdelTest": "False",
      "englishTitle": "Un bon bock",
      "isAdult": 1,
      "movieId": 4,
      "movieType": "short",
      "originalTitle": "Un bon bock",
      "runtimeMinutes": "12"
    },
    {
      "Year": 1893,
      "bechdelScore": 0,
      "bechdelTest": "False",
      "englishTitle": "Blacksmith Scene",
      "isAdult": 1,
      "movieId": 5,
      "movieType": "short",
      "originalTitle": "Blacksmith Scene",
      "runtimeMinutes": "1"
    },
    {
      "Year": 1894,
      "bechdelScore": 0,
      "bechdelTest": "False",
      "englishTitle": "Chinese Opium Den",
      "isAdult": 1,
      "movieId": 6,
      "movieType": "short",
      "originalTitle": "Chinese Opium Den",
      "runtimeMinutes": "1"
    },
    {
      "Year": 1894,
      "bechdelScore": 0,
      "bechdelTest": "False",
      "englishTitle": "Corbett and Courtney Before the Kinetograph",
      "isAdult": 1,
      "movieId": 7,
      "movieType": "short",
      "originalTitle": "Corbett and Courtney Before the Kinetograph",
      "runtimeMinutes": "1"
    },
    {
      "Year": 1894,
      "bechdelScore": 0,
      "bechdelTest": "False",
      "englishTitle": "Edison Kinetoscopic Record of a Sneeze",
      "isAdult": 1,
      "movieId": 8,
      "movieType": "short",
      "originalTitle": "Edison Kinetoscopic Record of a Sneeze",
      "runtimeMinutes": "1"
    },
    {
      "Year": 1894,
      "bechdelScore": 0,
      "bechdelTest": "False",
      "englishTitle": "Miss Jerry",
      "isAdult": 1,
      "movieId": 9,
      "movieType": "movie",
      "originalTitle": "Miss Jerry",
      "runtimeMinutes": "45"
    },
    {
      "Year": 1895,
      "bechdelScore": 1,
      "bechdelTest": "False",
      "englishTitle": "Akrobatisches Potpourri",
      "isAdult": 1,
      "movieId": 11,
      "movieType": "short",
      "originalTitle": "Akrobatisches Potpourri",
      "runtimeMinutes": "1"
    },
    {
      "Year": 1896,
      "bechdelScore": 0,
      "bechdelTest": "False",
      "englishTitle": "The Arrival of a Train",
      "isAdult": 1,
      "movieId": 12,
      "movieType": "short",
      "originalTitle": "L'arriv\u00e9e d'un train \u00e0 La Ciotat",
      "runtimeMinutes": "1"
    },
    {
      "Year": 1895,
      "bechdelScore": 0,
      "bechdelTest": "False",
      "englishTitle": "The Waterer Watered",
      "isAdult": 1,
      "movieId": 14,
      "movieType": "short",
      "originalTitle": "L'arroseur arros\u00e9",
      "runtimeMinutes": "1"
    },
    {
      "Year": 1894,
      "bechdelScore": 0,
      "bechdelTest": "False",
      "englishTitle": "Autour d'une cabine",
      "isAdult": 1,
      "movieId": 15,
      "movieType": "short",
      "originalTitle": "Autour d'une cabine",
      "runtimeMinutes": "2"
    },
    {
      "Year": 1895,
      "bechdelScore": 0,
      "bechdelTest": "False",
      "englishTitle": "Boat Leaving the Port",
      "isAdult": 1,
      "movieId": 16,
      "movieType": "short",
      "originalTitle": "Barque sortant du port",
      "runtimeMinutes": "1"
    },
    {
      "Year": 1895,
      "bechdelScore": 0,
      "bechdelTest": "False",
      "englishTitle": "Italienischer Bauerntanz",
      "isAdult": 1,
      "movieId": 17,
      "movieType": "short",
      "originalTitle": "Italienischer Bauerntanz",
      "runtimeMinutes": "1"
    },
    {
      "Year": 1895,
      "bechdelScore": 0,
      "bechdelTest": "False",
      "englishTitle": "Blacksmith Scene",
      "isAdult": 1,
      "movieId": 22,
      "movieType": "short",
      "originalTitle": "Les forgerons",
      "runtimeMinutes": "1"
    },
    {
      "Year": 1895,
      "bechdelScore": 1,
      "bechdelTest": "False",
      "englishTitle": "Baby's Meal",
      "isAdult": 1,
      "movieId": 29,
      "movieType": "short",
      "originalTitle": "Repas de b\u00e9b\u00e9",
      "runtimeMinutes": "1"
    },
    {
      "Year": 1897,
      "bechdelScore": 0,
      "bechdelTest": "False",
      "englishTitle": "Bataille de neige",
      "isAdult": 1,
      "movieId": 41,
      "movieType": "short",
      "originalTitle": "Bataille de neige",
      "runtimeMinutes": "1"
    },
    {
      "Year": 1896,
      "bechdelScore": 0,
      "bechdelTest": "False",
      "englishTitle": "The House of the Devil",
      "isAdult": 1,
      "movieId": 91,
      "movieType": "short",
      "originalTitle": "Le manoir du diable",
      "runtimeMinutes": "3"
    },
    {
      "Year": 1896,
      "bechdelScore": 0,
      "bechdelTest": "False",
      "englishTitle": "A Terrible Night",
      "isAdult": 1,
      "movieId": 131,
      "movieType": "short",
      "originalTitle": "Une nuit terrible",
      "runtimeMinutes": "1"
    },
    {
      "Year": 1898,
      "bechdelScore": 0,
      "bechdelTest": "False",
      "englishTitle": "The Astronomer's Dream; or, the Man in the Moon",
      "isAdult": 1,
      "movieId": 211,
      "movieType": "short",
      "originalTitle": "La lune \u00e0 un m\u00e8tre",
      "runtimeMinutes": "3"
    },
    {
      "Year": 1899,
      "bechdelScore": 3,
      "bechdelTest": "True",
      "englishTitle": "Cinderella",
      "isAdult": 1,
      "movieId": 230,
      "movieType": "short",
      "originalTitle": "Cendrillon",
      "runtimeMinutes": "6"
    },
    {
      "Year": 1899,
      "bechdelScore": 0,
      "bechdelTest": "False",
      "englishTitle": "A Turn of the Century Illusionist",
      "isAdult": 1,
      "movieId": 246,
      "movieType": "short",
      "originalTitle": "L'impressionniste fin de si\u00e8cle",
      "runtimeMinutes": "1"
    },
    {
      "Year": 1900,
      "bechdelScore": 0,
      "bechdelTest": "False",
      "englishTitle": "As Seen Through a Telescope",
      "isAdult": 1,
      "movieId": 272,
      "movieType": "short",
      "originalTitle": "As Seen Through a Telescope",
      "runtimeMinutes": "1"
    },
    {
      "Year": 1900,
      "bechdelScore": 0,
      "bechdelTest": "False",
      "englishTitle": "The Enchanted Drawing",
      "isAdult": 1,
      "movieId": 300,
      "movieType": "short",
      "originalTitle": "The Enchanted Drawing",
      "runtimeMinutes": "2"
    },
    {
      "Year": 1900,
      "bechdelScore": 0,
      "bechdelTest": "False",
      "englishTitle": "Grandma's Reading Glass",
      "isAdult": 1,
      "movieId": 304,
      "movieType": "short",
      "originalTitle": "Grandma's Reading Glass",
      "runtimeMinutes": "2"
    },
    {
      "Year": 1900,
      "bechdelScore": 0,
      "bechdelTest": "False",
      "englishTitle": "Le duel d'Hamlet",
      "isAdult": 1,
      "movieId": 306,
      "movieType": "short",
      "originalTitle": "Le duel d'Hamlet",
      "runtimeMinutes": "2"
    },
    {
      "Year": 1900,
      "bechdelScore": 0,
      "bechdelTest": "False",
      "englishTitle": "Let Me Dream Again",
      "isAdult": 1,
      "movieId": 313,
      "movieType": "short",
      "originalTitle": "Let Me Dream Again",
      "runtimeMinutes": "1"
    },
    {
      "Year": 1901,
      "bechdelScore": 0,
      "bechdelTest": "False",
      "englishTitle": "The India Rubber Head",
      "isAdult": 1,
      "movieId": 359,
      "movieType": "short",
      "originalTitle": "L'homme \u00e0 la t\u00eate en caoutchouc",
      "runtimeMinutes": "3"
    },
    {
      "Year": 1902,
      "bechdelScore": 0,
      "bechdelTest": "False",
      "englishTitle": "The Devil's Money Bags",
      "isAdult": 1,
      "movieId": 413,
      "movieType": "short",
      "originalTitle": "Les tr\u00e9sors de satan",
      "runtimeMinutes": "3"
    }
  ],
  "next_page": "/movies?page=1&page_size=30"
}
